chas/__init__.py
chas/command_line.py
chas/counters.py
chas/exceptions.py
chas/http_server.py
chas/job.py
chas/logger.py
chas/scheduler.py
chas/state.py
chas/static/.DS_Store
chas/static/jquery.js
chas/static/main.js
chas/static/semantic.css
chas/templates/main.html
chas-0.6.0.dist-info/METADATA
chas-0.6.0.dist-info/WHEEL
chas-0.6.0.dist-info/entry_points.txt
chas-0.6.0.dist-info/top_level.txt
chas-0.6.0.dist-info/RECORD
