Metadata-Version: 2.1
Name: chas
Version: 0.6.0
Summary: Framework for creating and running cron jobs.
Home-page: https://github.com/lukasotocerny/chas
Author: Lukas Cerny
Author-email: lukas.cerny@exponea.com
License: UNKNOWN
Platform: UNKNOWN
Classifier: Programming Language :: Python :: 3.6
Requires-Dist: flask (==1.1.2)
Requires-Dist: prometheus-flask-exporter (==0.15.4)
Requires-Dist: prometheus-client (==0.8.0)
Requires-Dist: croniter (==0.3.34)
